{"五号位总数": 26, "四号位总数": 24, "六号位属性": {"防御加成": 4, "暴击": 1, "攻击加成": 9, "生命加成": 8, "暴击伤害": 0}, "反枕": {"六号位属性": {"防御加成": 0, "暴击": 0, "攻击加成": 2, "生命加成": 4, "暴击伤害": 0}, "五星": 32, "一号位": 5, "二号位": 9, "四号位属性": {"防御加成": 0, "效果抵抗": 1, "攻击加成": 2, "生命加成": 1, "效果命中": 0}, "总数": 33, "六星": 1, "六号位": 6, "五号位": 5, "三号位": 4, "四号位": 4, "二号位属性": {"防御加成": 2, "攻击加成": 3, "生命加成": 2, "速度": 2}}, "针女": {"六号位属性": {"防御加成": 1, "暴击": 0, "攻击加成": 0, "生命加成": 1, "暴击伤害": 0}, "五星": 42, "一号位": 8, "二号位": 9, "四号位属性": {"防御加成": 3, "效果抵抗": 1, "攻击加成": 2, "生命加成": 5, "效果命中": 0}, "总数": 48, "六星": 6, "六号位": 2, "五号位": 11, "三号位": 7, "四号位": 11, "二号位属性": {"防御加成": 4, "攻击加成": 2, "生命加成": 3, "速度": 0}}, "心眼": {"六号位属性": {"防御加成": 2, "暴击": 0, "攻击加成": 5, "生命加成": 2, "暴击伤害": 0}, "五星": 37, "一号位": 9, "二号位": 6, "四号位属性": {"防御加成": 4, "效果抵抗": 0, "攻击加成": 0, "生命加成": 1, "效果命中": 1}, "总数": 41, "六星": 4, "六号位": 9, "五号位": 5, "三号位": 6, "四号位": 6, "二号位属性": {"防御加成": 2, "攻击加成": 1, "生命加成": 2, "速度": 1}}, "五星御魂总数": 14, "六星御魂总数": 142, "四号位属性": {"防御加成": 7, "效果抵抗": 2, "攻击加成": 6, "生命加成": 8, "效果命中": 1}, "六号位总数": 22, "金色御魂总数": 156, "二号位总数": 32, "树妖": {"六号位属性": {"防御加成": 1, "暴击": 1, "攻击加成": 2, "生命加成": 1, "暴击伤害": 0}, "五星": 31, "一号位": 8, "二号位": 8, "四号位属性": {"防御加成": 0, "效果抵抗": 0, "攻击加成": 2, "生命加成": 1, "效果命中": 0}, "总数": 34, "六星": 3, "六号位": 5, "五号位": 5, "三号位": 5, "四号位": 3, "二号位属性": {"防御加成": 3, "攻击加成": 2, "生命加成": 1, "速度": 2}}, "一号位总数": 30, "二号位属性": {"防御加成": 11, "攻击加成": 8, "生命加成": 8, "速度": 5}, "三号位总数": 22}